Metadata-Version: 2.4
Name: switchprint
Version: 2.1.2
Summary: Production-ready Python library for detecting multilingual code-switching patterns with 100% test coverage, advanced threshold systems, and robust API stability
Author-email: Aahad Vakani <aahadvakani@gmail.com>
License-Expression: MIT
Project-URL: Homepage, https://github.com/aahadvakani/switchprint
Project-URL: Repository, https://github.com/aahadvakani/switchprint
Project-URL: Bug Reports, https://github.com/aahadvakani/switchprint/issues
Project-URL: Changelog, https://github.com/aahadvakani/switchprint/blob/main/CHANGELOG.md
Keywords: nlp,multilingual,code-switching,language-detection,ai,linguistics
Classifier: Development Status :: 5 - Production/Stable
Classifier: Intended Audience :: Developers
Classifier: Intended Audience :: Science/Research
Classifier: Operating System :: OS Independent
Classifier: Programming Language :: Python :: 3
Classifier: Programming Language :: Python :: 3.8
Classifier: Programming Language :: Python :: 3.9
Classifier: Programming Language :: Python :: 3.10
Classifier: Programming Language :: Python :: 3.11
Classifier: Programming Language :: Python :: 3.12
Classifier: Topic :: Scientific/Engineering :: Artificial Intelligence
Classifier: Topic :: Text Processing :: Linguistic
Classifier: Topic :: Software Development :: Libraries :: Python Modules
Requires-Python: >=3.8
License-File: LICENSE
Requires-Dist: langdetect==1.0.9
Requires-Dist: sentence-transformers<3.0.0,>=2.7.0
Requires-Dist: faiss-cpu<2.0.0,>=1.8.0
Requires-Dist: numpy<2.0.0,>=1.24.0
Requires-Dist: scikit-learn<2.0.0,>=1.3.0
Provides-Extra: fasttext
Requires-Dist: fasttext>=0.9.2; extra == "fasttext"
Provides-Extra: transformers
Requires-Dist: transformers<5.0.0,>=4.39.0; extra == "transformers"
Requires-Dist: torch>=2.2.0; extra == "transformers"
Provides-Extra: analysis
Requires-Dist: pandas<3.0.0,>=2.0.0; extra == "analysis"
Requires-Dist: mteb>=1.14.0; extra == "analysis"
Provides-Extra: ui
Requires-Dist: streamlit>=1.32.0; extra == "ui"
Requires-Dist: flask>=2.3.0; extra == "ui"
Requires-Dist: click>=8.1.0; extra == "ui"
Requires-Dist: plotly>=5.17.0; extra == "ui"
Provides-Extra: dev
Requires-Dist: pytest>=7.0.0; extra == "dev"
Requires-Dist: black>=23.0.0; extra == "dev"
Requires-Dist: flake8>=6.0.0; extra == "dev"
Requires-Dist: twine>=4.0.0; extra == "dev"
Requires-Dist: build>=0.10.0; extra == "dev"
Provides-Extra: all
Requires-Dist: fasttext>=0.9.2; extra == "all"
Requires-Dist: transformers<5.0.0,>=4.39.0; extra == "all"
Requires-Dist: torch>=2.2.0; extra == "all"
Requires-Dist: pandas<3.0.0,>=2.0.0; extra == "all"
Requires-Dist: mteb>=1.14.0; extra == "all"
Requires-Dist: streamlit>=1.32.0; extra == "all"
Requires-Dist: flask>=2.3.0; extra == "all"
Requires-Dist: click>=8.1.0; extra == "all"
Requires-Dist: plotly>=5.17.0; extra == "all"
Requires-Dist: pytest>=7.0.0; extra == "all"
Requires-Dist: black>=23.0.0; extra == "all"
Requires-Dist: flake8>=6.0.0; extra == "all"
Requires-Dist: twine>=4.0.0; extra == "all"
Requires-Dist: build>=0.10.0; extra == "all"
Dynamic: license-file
